mailer/__init__.py
mailer/exceptions.py
mailer/login.py
mailer/mailer.py
mailer/send.py
mailer/utils.py
quick_mailer-2022.2.22.dist-info/LICENSE
quick_mailer-2022.2.22.dist-info/METADATA
quick_mailer-2022.2.22.dist-info/WHEEL
quick_mailer-2022.2.22.dist-info/top_level.txt
quick_mailer-2022.2.22.dist-info/RECORD
