Metadata-Version: 2.1
Name: quick-mailer
Version: 2022.2.22
Summary: This Module help you to send fast Email.🌸
Home-page: https://github.com/Al-Taie/quick-mailer
Author: Ahmed Al-Taie
Author-email: agprosup@gmail.com
License: UNKNOWN
Keywords: smtp,mail,gmail,email
Platform: UNKNOWN
Classifier: Programming Language :: Python :: 3
Classifier: License :: OSI Approved :: MIT License
Classifier: Operating System :: OS Independent
License-File: LICENSE
